cyclical/__init__.py
cyclical/cyclical.py
cyclical-1.0.2.dist-info/LICENSE
cyclical-1.0.2.dist-info/METADATA
cyclical-1.0.2.dist-info/WHEEL
cyclical-1.0.2.dist-info/top_level.txt
cyclical-1.0.2.dist-info/RECORD
