Metadata-Version: 2.1
Name: cyclical
Version: 1.0.2
Summary: Encode item list into cyclical
Home-page: https://github.com/jojoee/cyclical
Author: Nathachai Thongniran
Author-email: inid3a@gmail.com
License: MIT
Keywords: cyclical,cyclic,normalization,normalize
Classifier: License :: OSI Approved :: MIT License
Classifier: Operating System :: OS Independent
Classifier: Programming Language :: Python :: 3
Classifier: Programming Language :: Python :: 3.7
License-File: LICENSE
